{
    "0": "{\"id\":0,\"name\":\"Appliance ebf1\",\"type\":\"Smoke detector\",\"createdAt\":\"2022-01-27T02:11:04.343Z\"}",
    "1": "{\"id\":1,\"name\":\"Appliance 2131232131\",\"type\":\"Smoke detector\",\"createdAt\":\"2022-01-28T16:13:23.444Z\",\"lastRebooted\":\"2022-12-29T14:49:54.494Z\"}",
    "2": "{\"id\":2,\"name\":\"Appliance 3f8e\",\"type\":\"Smoke detector\",\"createdAt\":\"2022-01-11T07:04:11.043Z\"}",
    "4": "{\"id\":4,\"name\":\"Appliance 8921\",\"type\":\"Set top box\",\"createdAt\":\"2022-01-24T20:38:40.792Z\"}",
    "5": "{\"id\":5,\"name\":\"Appliance 6d91\",\"type\":\"Smoke detector\",\"createdAt\":\"2022-01-02T06:22:48.022Z\"}",
    "6": "{\"id\":6,\"name\":\"Appliance 67d9\",\"type\":\"Set top box\",\"createdAt\":\"2022-01-06T08:06:49.595Z\"}",
    "7": "{\"id\":7,\"name\":\"Appliance 8051\",\"type\":\"Set top box\",\"createdAt\":\"2022-01-06T23:35:40.862Z\"}",
    "8": "{\"id\":8,\"name\":\"Appliance 6abd\",\"type\":\"Smoke detector\",\"createdAt\":\"2022-01-10T23:36:33.769Z\"}",
    "9": "{\"id\":9,\"name\":\"Appliance e4d4\",\"type\":\"Smoke detector\",\"createdAt\":\"2022-01-14T00:39:36.713Z\"}",
    "10": "{\"id\":10,\"name\":\"Appliance 2a02\",\"type\":\"Smoke detector\",\"createdAt\":\"2022-01-14T06:27:05.937Z\"}",
    "11": "{\"id\":11,\"name\":\"Appliance cb20\",\"type\":\"Set top box\",\"createdAt\":\"2022-01-09T21:17:53.386Z\"}",
    "12": "{\"id\":12,\"name\":\"Appliance 2062\",\"type\":\"Smoke detector\",\"createdAt\":\"2022-01-26T06:42:33.755Z\"}",
    "13": "{\"id\":13,\"name\":\"Appliance 6169\",\"type\":\"Lightbulb\",\"createdAt\":\"2022-01-12T21:00:20.125Z\"}",
    "14": "{\"id\":14,\"name\":\"Appliance 6984\",\"type\":\"Lightbulb\",\"createdAt\":\"2022-01-18T14:02:03.344Z\"}",
    "15": "{\"id\":15,\"name\":\"Appliance 75e8\",\"type\":\"Lightbulb\",\"createdAt\":\"2022-01-22T01:07:02.715Z\"}",
    "16": "{\"id\":16,\"name\":\"Appliance 26eb\",\"type\":\"Smoke detector\",\"createdAt\":\"2022-01-10T16:04:04.420Z\"}",
    "17": "{\"id\":17,\"name\":\"Appliance ee55\",\"type\":\"Lightbulb\",\"createdAt\":\"2022-01-18T16:50:42.657Z\"}",
    "18": "{\"id\":18,\"name\":\"Appliance eb57\",\"type\":\"Smoke detector\",\"createdAt\":\"2022-01-20T22:55:13.939Z\"}",
    "19": "{\"id\":19,\"name\":\"Appliance 1e9a\",\"type\":\"Smoke detector\",\"createdAt\":\"2022-01-23T10:46:46.473Z\"}",
    "20": "{\"id\":20,\"name\":\"Appliance bb64\",\"type\":\"Set top box\",\"createdAt\":\"2022-01-14T15:57:53.186Z\"}",
    "21": "{\"id\":21,\"name\":\"Appliance 764d\",\"type\":\"Lightbulb\",\"createdAt\":\"2022-01-06T20:06:13.641Z\"}",
    "22": "{\"id\":22,\"name\":\"Appliance 74dc\",\"type\":\"Smoke detector\",\"createdAt\":\"2022-01-03T22:01:51.364Z\"}",
    "23": "{\"id\":23,\"name\":\"Appliance 5e76\",\"type\":\"Smoke detector\",\"createdAt\":\"2022-01-16T19:00:07.018Z\"}",
    "24": "{\"id\":24,\"name\":\"Appliance 4aec\",\"type\":\"Smoke detector\",\"createdAt\":\"2022-01-25T02:00:48.988Z\"}",
    "25": "{\"id\":25,\"name\":\"Appliance 75a2\",\"type\":\"Lightbulb\",\"createdAt\":\"2022-01-19T02:54:14.913Z\"}",
    "26": "{\"id\":26,\"name\":\"Appliance f569\",\"type\":\"Set top box\",\"createdAt\":\"2022-01-06T13:38:08.913Z\"}",
    "27": "{\"id\":27,\"name\":\"Appliance f5f6\",\"type\":\"Set top box\",\"createdAt\":\"2022-01-02T00:24:19.873Z\"}",
    "28": "{\"id\":28,\"name\":\"Appliance 77d7\",\"type\":\"Set top box\",\"createdAt\":\"2022-01-14T13:26:49.932Z\"}",
    "29": "{\"id\":29,\"name\":\"Appliance 0af7\",\"type\":\"Set top box\",\"createdAt\":\"2022-01-27T01:02:32.654Z\"}",
    "30": "{\"id\":30,\"name\":\"Appliance 4e6c\",\"type\":\"Lightbulb\",\"createdAt\":\"2022-01-14T15:26:35.785Z\"}",
    "31": "{\"id\":31,\"name\":\"Appliance ae21\",\"type\":\"Lightbulb\",\"createdAt\":\"2022-01-24T16:39:43.635Z\"}",
    "32": "{\"id\":32,\"name\":\"Appliance e160\",\"type\":\"Smoke detector\",\"createdAt\":\"2022-01-23T02:21:06.911Z\"}",
    "33": "{\"id\":33,\"name\":\"Appliance 4874\",\"type\":\"Set top box\",\"createdAt\":\"2022-01-07T12:45:41.511Z\"}",
    "34": "{\"id\":34,\"name\":\"Appliance 1c60\",\"type\":\"Set top box\",\"createdAt\":\"2022-01-06T10:57:20.961Z\"}",
    "35": "{\"id\":35,\"name\":\"Appliance e512\",\"type\":\"Set top box\",\"createdAt\":\"2022-01-03T07:15:54.919Z\"}",
    "36": "{\"id\":36,\"name\":\"Appliance 9eb1\",\"type\":\"Smoke detector\",\"createdAt\":\"2022-01-02T08:39:15.930Z\"}",
    "37": "{\"id\":37,\"name\":\"Appliance d3fe\",\"type\":\"Set top box\",\"createdAt\":\"2022-01-06T05:39:45.134Z\"}",
    "38": "{\"id\":38,\"name\":\"Appliance 75ca\",\"type\":\"Lightbulb\",\"createdAt\":\"2022-01-04T20:12:36.652Z\"}",
    "39": "{\"id\":39,\"name\":\"Appliance f945\",\"type\":\"Set top box\",\"createdAt\":\"2022-01-15T23:40:05.307Z\"}",
    "40": "{\"id\":40,\"name\":\"Appliance b393\",\"type\":\"Smoke detector\",\"createdAt\":\"2022-01-10T20:31:30.995Z\"}",
    "41": "{\"id\":41,\"name\":\"Appliance acfe\",\"type\":\"Smoke detector\",\"createdAt\":\"2022-01-27T15:37:50.038Z\"}",
    "42": "{\"id\":42,\"name\":\"Appliance df69\",\"type\":\"Smoke detector\",\"createdAt\":\"2022-01-09T23:08:07.933Z\"}",
    "43": "{\"id\":43,\"name\":\"Appliance 703a\",\"type\":\"Smoke detector\",\"createdAt\":\"2022-01-05T20:12:24.389Z\"}",
    "44": "{\"id\":44,\"name\":\"Appliance b51f\",\"type\":\"Smoke detector\",\"createdAt\":\"2022-01-20T18:01:02.984Z\"}",
    "45": "{\"id\":45,\"name\":\"Appliance dc24\",\"type\":\"Set top box\",\"createdAt\":\"2022-01-21T09:53:32.651Z\"}",
    "46": "{\"id\":46,\"name\":\"Appliance 94a6\",\"type\":\"Lightbulb\",\"createdAt\":\"2022-01-10T20:46:58.185Z\"}",
    "47": "{\"id\":47,\"name\":\"Appliance 2988\",\"type\":\"Set top box\",\"createdAt\":\"2022-01-20T15:18:36.583Z\"}",
    "48": "{\"id\":48,\"name\":\"Appliance 04d3\",\"type\":\"Set top box\",\"createdAt\":\"2022-01-15T01:30:00.307Z\"}",
    "49": "{\"id\":49,\"name\":\"Appliance 80e0\",\"type\":\"Set top box\",\"createdAt\":\"2022-01-20T08:49:16.868Z\"}",
    "50": "{\"id\":50,\"name\":\"Appliance eca7\",\"type\":\"Set top box\",\"createdAt\":\"2022-01-27T02:46:00.834Z\"}",
    "51": "{\"id\":51,\"name\":\"Appliance dcb1\",\"type\":\"Set top box\",\"createdAt\":\"2022-01-17T08:44:31.785Z\"}",
    "52": "{\"id\":52,\"name\":\"Appliance b25c\",\"type\":\"Lightbulb\",\"createdAt\":\"2022-01-07T19:03:30.099Z\"}",
    "53": "{\"id\":53,\"name\":\"Appliance de01\",\"type\":\"Lightbulb\",\"createdAt\":\"2022-01-04T23:20:00.315Z\"}",
    "54": "{\"id\":54,\"name\":\"Appliance e64d\",\"type\":\"Lightbulb\",\"createdAt\":\"2022-01-03T19:45:10.925Z\"}",
    "55": "{\"id\":55,\"name\":\"Appliance 412b\",\"type\":\"Smoke detector\",\"createdAt\":\"2022-01-06T06:20:16.383Z\"}",
    "56": "{\"id\":56,\"name\":\"Appliance ab38\",\"type\":\"Smoke detector\",\"createdAt\":\"2022-01-03T19:17:20.806Z\"}",
    "57": "{\"id\":57,\"name\":\"Appliance e1eb\",\"type\":\"Set top box\",\"createdAt\":\"2022-01-05T02:46:15.223Z\"}",
    "58": "{\"id\":58,\"name\":\"Appliance 4a28\",\"type\":\"Set top box\",\"createdAt\":\"2022-01-26T16:50:15.761Z\"}",
    "59": "{\"id\":59,\"name\":\"Appliance b0ba\",\"type\":\"Smoke detector\",\"createdAt\":\"2022-01-29T10:57:41.253Z\"}",
    "60": "{\"id\":60,\"name\":\"Appliance 35bf\",\"type\":\"Lightbulb\",\"createdAt\":\"2022-01-03T11:20:08.155Z\"}",
    "61": "{\"id\":61,\"name\":\"Appliance 2ce3\",\"type\":\"Lightbulb\",\"createdAt\":\"2022-01-26T16:30:51.327Z\"}",
    "62": "{\"id\":62,\"name\":\"Appliance bb4a\",\"type\":\"Smoke detector\",\"createdAt\":\"2022-01-10T14:21:14.758Z\"}",
    "63": "{\"id\":63,\"name\":\"Appliance aba9\",\"type\":\"Lightbulb\",\"createdAt\":\"2022-01-19T05:11:02.240Z\"}",
    "64": "{\"id\":64,\"name\":\"Appliance 5408\",\"type\":\"Lightbulb\",\"createdAt\":\"2022-01-14T20:28:14.155Z\"}",
    "65": "{\"id\":65,\"name\":\"Appliance a240\",\"type\":\"Smoke detector\",\"createdAt\":\"2022-01-28T01:37:21.790Z\"}",
    "66": "{\"id\":66,\"name\":\"Appliance 2a4d\",\"type\":\"Set top box\",\"createdAt\":\"2022-01-13T09:27:06.096Z\"}",
    "67": "{\"id\":67,\"name\":\"Appliance 7ba4\",\"type\":\"Smoke detector\",\"createdAt\":\"2022-01-16T08:07:05.019Z\"}",
    "68": "{\"id\":68,\"name\":\"Appliance 0c66\",\"type\":\"Set top box\",\"createdAt\":\"2022-01-04T03:06:46.689Z\"}",
    "69": "{\"id\":69,\"name\":\"Appliance a76f\",\"type\":\"Set top box\",\"createdAt\":\"2022-01-15T19:21:46.868Z\"}",
    "70": "{\"id\":70,\"name\":\"Appliance 8b23\",\"type\":\"Lightbulb\",\"createdAt\":\"2022-01-22T08:28:11.519Z\"}",
    "71": "{\"id\":71,\"name\":\"Appliance f405\",\"type\":\"Lightbulb\",\"createdAt\":\"2022-01-29T14:18:56.407Z\"}",
    "72": "{\"id\":72,\"name\":\"Appliance bfcb\",\"type\":\"Lightbulb\",\"createdAt\":\"2022-01-16T01:53:48.524Z\"}",
    "73": "{\"id\":73,\"name\":\"Appliance 0d54\",\"type\":\"Smoke detector\",\"createdAt\":\"2022-01-19T14:07:53.068Z\"}",
    "74": "{\"id\":74,\"name\":\"Appliance d912\",\"type\":\"Smoke detector\",\"createdAt\":\"2022-01-21T11:17:30.863Z\"}",
    "75": "{\"id\":75,\"name\":\"Appliance 1f35\",\"type\":\"Lightbulb\",\"createdAt\":\"2022-01-13T03:11:29.534Z\"}",
    "76": "{\"id\":76,\"name\":\"Appliance ea29\",\"type\":\"Lightbulb\",\"createdAt\":\"2022-01-17T12:16:43.747Z\"}",
    "77": "{\"id\":77,\"name\":\"Appliance 4468\",\"type\":\"Lightbulb\",\"createdAt\":\"2022-01-27T13:00:51.971Z\"}",
    "78": "{\"id\":78,\"name\":\"Appliance 20c8\",\"type\":\"Set top box\",\"createdAt\":\"2022-01-10T03:17:56.342Z\"}",
    "79": "{\"id\":79,\"name\":\"Appliance eecc\",\"type\":\"Lightbulb\",\"createdAt\":\"2022-01-21T12:43:33.351Z\"}",
    "80": "{\"id\":80,\"name\":\"Appliance c82c\",\"type\":\"Set top box\",\"createdAt\":\"2022-01-11T20:08:46.683Z\"}",
    "81": "{\"id\":81,\"name\":\"Appliance 0385\",\"type\":\"Lightbulb\",\"createdAt\":\"2022-01-19T17:52:23.947Z\"}",
    "82": "{\"id\":82,\"name\":\"Appliance 227b\",\"type\":\"Lightbulb\",\"createdAt\":\"2022-01-27T06:54:23.923Z\"}",
    "83": "{\"id\":83,\"name\":\"Appliance f573\",\"type\":\"Smoke detector\",\"createdAt\":\"2022-01-15T03:18:48.641Z\"}",
    "84": "{\"id\":84,\"name\":\"Appliance ece7\",\"type\":\"Set top box\",\"createdAt\":\"2022-01-20T00:58:51.128Z\"}",
    "85": "{\"id\":85,\"name\":\"Appliance 3aa5\",\"type\":\"Smoke detector\",\"createdAt\":\"2022-01-06T01:14:21.098Z\"}",
    "86": "{\"id\":86,\"name\":\"Appliance 91d6\",\"type\":\"Set top box\",\"createdAt\":\"2022-01-25T11:46:03.770Z\"}",
    "87": "{\"id\":87,\"name\":\"Appliance f8a9\",\"type\":\"Set top box\",\"createdAt\":\"2022-01-03T00:50:17.962Z\"}",
    "88": "{\"id\":88,\"name\":\"Appliance b23b\",\"type\":\"Lightbulb\",\"createdAt\":\"2022-01-02T18:54:33.988Z\"}",
    "89": "{\"id\":89,\"name\":\"Appliance 3ad3\",\"type\":\"Lightbulb\",\"createdAt\":\"2022-01-28T00:10:54.982Z\"}",
    "90": "{\"id\":90,\"name\":\"Appliance e8bc\",\"type\":\"Lightbulb\",\"createdAt\":\"2022-01-02T21:39:11.100Z\"}",
    "91": "{\"id\":91,\"name\":\"Appliance de3c\",\"type\":\"Set top box\",\"createdAt\":\"2022-01-13T03:59:19.573Z\"}",
    "92": "{\"id\":92,\"name\":\"Appliance bcec\",\"type\":\"Set top box\",\"createdAt\":\"2022-01-20T01:36:39.612Z\"}",
    "93": "{\"id\":93,\"name\":\"Appliance f257\",\"type\":\"Smoke detector\",\"createdAt\":\"2022-01-12T23:25:58.402Z\"}",
    "94": "{\"id\":94,\"name\":\"Appliance a484\",\"type\":\"Lightbulb\",\"createdAt\":\"2022-01-13T00:23:38.835Z\"}",
    "95": "{\"id\":95,\"name\":\"Appliance 33c5\",\"type\":\"Smoke detector\",\"createdAt\":\"2022-01-16T03:47:26.794Z\"}",
    "96": "{\"id\":96,\"name\":\"Appliance ac23\",\"type\":\"Set top box\",\"createdAt\":\"2022-01-06T07:24:57.047Z\"}",
    "97": "{\"id\":97,\"name\":\"Appliance 5251\",\"type\":\"Set top box\",\"createdAt\":\"2022-01-21T06:34:30.873Z\"}",
    "98": "{\"id\":98,\"name\":\"Appliance 86cf\",\"type\":\"Lightbulb\",\"createdAt\":\"2022-01-06T05:32:29.590Z\"}",
    "99": "{\"id\":99,\"name\":\"Appliance 2a47\",\"type\":\"Set top box\",\"createdAt\":\"2022-01-22T10:44:23.807Z\"}",
    "100": "{\"id\":100,\"type\":\"Lightbulb\",\"name\":\"Appliance 2131232131\",\"createdAt\":\"2022-01-03T18:14:39.714Z\"}",
    "101": "{\"id\":101,\"type\":\"Lightbulb\",\"name\":\"Appliance 2131232131\",\"createdAt\":\"2022-01-27T15:35:06.741Z\"}",
    "102": "{\"id\":102,\"type\":\"Lightbulb\",\"name\":\"Appliance 2131232131\",\"createdAt\":\"2022-01-26T08:04:30.284Z\"}"
}